color_string/__init__.py
color_string/__version__.py
color_string/color_string.py
color_string-0.0.0.dist-info/DESCRIPTION.rst
color_string-0.0.0.dist-info/METADATA
color_string-0.0.0.dist-info/RECORD
color_string-0.0.0.dist-info/WHEEL
color_string-0.0.0.dist-info/metadata.json
color_string-0.0.0.dist-info/top_level.txt
